[
  {
    "provincia": "Distrito Nacional",
    "value": 72.55
  },
  {
    "provincia": "Azua",
    "value": 320.42999999999995
  },
  {
    "provincia": "Baoruco",
    "value": 315.52
  },
  {
    "provincia": "Barahona",
    "value": 336.21999999999997
  },
  {
    "provincia": "Dajabón",
    "value": 320.65999999999997
  },
  {
    "provincia": "Duarte",
    "value": 341.23
  },
  {
    "provincia": "Elías Piña",
    "value": 320.5
  },
  {
    "provincia": "El Seibo",
    "value": 151.66
  },
  {
    "provincia": "Espaillat",
    "value": 315.1
  },
  {
    "provincia": "Independencia",
    "value": 325.08
  },
  {
    "provincia": "La Altagracia",
    "value": 157.32999999999998
  },
  {
    "provincia": "La Romana",
    "value": 204.14000000000001
  },
  {
    "provincia": "La Vega",
    "value": 261.45000000000005
  },
  {
    "provincia": "María Trinidad Sánchez",
    "value": 309.61
  },
  {
    "provincia": "Monte Cristi",
    "value": 289.01
  },
  {
    "provincia": "Pedernales",
    "value": 124.07000000000001
  },
  {
    "provincia": "Peravia",
    "value": 220.79999999999998
  },
  {
    "provincia": "Puerto Plata",
    "value": 354.14
  },
  {
    "provincia": "Hermanas Mirabal",
    "value": 171.54000000000002
  },
  {
    "provincia": "Samaná",
    "value": 191.41000000000003
  },
  {
    "provincia": "San Cristóbal",
    "value": 336.34000000000003
  },
  {
    "provincia": "San Juan",
    "value": 366.32000000000005
  },
  {
    "provincia": "San Pedro de Macorís",
    "value": 329.19
  },
  {
    "provincia": "Sanchez Ramírez",
    "value": 280.14
  },
  {
    "provincia": "Santiago",
    "value": 347.74000000000007
  },
  {
    "provincia": "Santiago Rodríguez",
    "value": 200.28
  },
  {
    "provincia": "Valverde",
    "value": 209.75
  },
  {
    "provincia": "Monseñor Nouel",
    "value": 208.06000000000003
  },
  {
    "provincia": "Monte Plata",
    "value": 335.95000000000005
  },
  {
    "provincia": "Hato Mayor",
    "value": 193.01
  },
  {
    "provincia": "San José de Ocoa",
    "value": 196.13000000000002
  }
]